[
    {
        "name": "US NHL Network",
        "id": "usnhlnetwork",
        "logo": "",
        "url": "http://xxip25.top:8080/hVvwU8/670199/253636",
        "categories": [
            "nhl"
        ],
        "country": ""
    },
    {
        "name": "USA Real NHL 08: EDM VS ANA (SNW Feed ) @ 10:30 pm",
        "id": "usarealnhl08edmvsanasnwfeed1030pm",
        "logo": "",
        "url": "http://tv2watch.icu:8080/7vGX9F/030546/262713",
        "categories": [
            "nhl"
        ],
        "country": ""
    },
    {
        "name": "USA Real NHL 06: VGK VS LAK (SN1 Feed ) @ 10:00 pm",
        "id": "usarealnhl06vgkvslaksn1feed1000pm",
        "logo": "",
        "url": "http://mytvstream.net:8080/RKu2Hy/559290/262711",
        "categories": [
            "nhl"
        ],
        "country": ""
    }
]