[
    {
        "name": ": ADANA SUPER FM",
        "id": "ADANASUPERFM.tr",
        "logo": "",
        "url": "http://yrtds0911.xyz:8080/cengizacar/KSSEP9J3tK/194721",
        "categories": [
            "radyo kanallari"
        ],
        "country": "TR"
    },
    {
        "name": ": TUNCELI RADYO MUNZUR",
        "id": "TUNCELIRADYOMUNZUR.tr",
        "logo": "",
        "url": "http://yrtds0911.xyz:8080/cengizacar/KSSEP9J3tK/194785",
        "categories": [
            "radyo kanallari"
        ],
        "country": "TR"
    }
]