[
    {
        "name": "TR: TRT TURK HEVC",
        "id": "trtrtturkhevc",
        "logo": "https://imagizer.imageshack.com/img923/2503/yH33d2.png",
        "url": "http://iptvmeister.de:8080/Erolkirval/zNjKCGEHGPcjA7S41/371818",
        "categories": [
            "tr | ulusal hevc"
        ],
        "country": ""
    },
    {
        "name": "TR: A HABER HEVC",
        "id": "trahaberhevc",
        "logo": "https://imagizer.imageshack.com/img924/4109/wlFN1G.png",
        "url": "http://iptvmeister.de:8080/Erolkirval/zNjKCGEHGPcjA7S41/371820",
        "categories": [
            "tr | ulusal hevc"
        ],
        "country": ""
    }
]