[
    {
        "name": "TV 100 HD",
        "id": "TV100HD.tr",
        "logo": "",
        "url": "http://yrtds0911.xyz:8080/hm6669/hm6669/200687",
        "categories": [
            "ulusal tv [hd]"
        ],
        "country": "TR"
    },
    {
        "name": "Atv HD",
        "id": "AtvHD.tr",
        "logo": "http://apkx.xyz/tv-tum-dunya-logolar/logolar/tv-tum-dunya-logolar/turkeyT/atv.png",
        "url": "http://yrtds0911.xyz:8080/cengizacar/KSSEP9J3tK/6266",
        "categories": [
            "ulusal tv [hd]"
        ],
        "country": "TR"
    },
    {
        "name": "TRT 2",
        "id": "trt2",
        "logo": "",
        "url": "http://ext2707.xyz:8080/Ferimahzari100/Scm2hxkJae/186242",
        "categories": [
            "ulusal tv [hd]"
        ],
        "country": ""
    }
]